wowsql_cli/__init__.py
wowsql_cli/api.py
wowsql_cli/auth.py
wowsql_cli/cli.py
wowsql_cli/config.py
wowsql_cli/exceptions.py
wowsql_cli/commands/__init__.py
wowsql_cli/commands/auth.py
wowsql_cli/commands/backup.py
wowsql_cli/commands/config_cmd.py
wowsql_cli/commands/db.py
wowsql_cli/commands/indexes.py
wowsql_cli/commands/init.py
wowsql_cli/commands/link.py
wowsql_cli/commands/local.py
wowsql_cli/commands/logs.py
wowsql_cli/commands/migration.py
wowsql_cli/commands/procedures.py
wowsql_cli/commands/projects.py
wowsql_cli/commands/secrets.py
wowsql_cli/commands/storage.py
wowsql_cli/commands/triggers.py
wowsql_cli/commands/types.py
wowsql_cli/commands/validate.py
wowsql_cli/commands/views.py
wowsql_cli/utils/__init__.py
wowsql_cli/utils/formatters.py
wowsql_cli-1.2.0.dist-info/METADATA
wowsql_cli-1.2.0.dist-info/WHEEL
wowsql_cli-1.2.0.dist-info/entry_points.txt
wowsql_cli-1.2.0.dist-info/top_level.txt
wowsql_cli-1.2.0.dist-info/RECORD
