Metadata-Version: 2.4
Name: wowsql-cli
Version: 1.2.0
Summary: WoWSQL Command Line Interface
Home-page: https://github.com/wowsql/cli
Author: WoWSQL Team
Author-email: support@wowsql.com
Project-URL: Documentation, https://wowsql.com/docs
Project-URL: Source, https://github.com/wowsql/cli
Project-URL: Tracker, https://github.com/wowsql/cli/issues
Keywords: wowsql cli database mysql backend api
Classifier: Development Status :: 4 - Beta
Classifier: Intended Audience :: Developers
Classifier: License :: OSI Approved :: MIT License
Classifier: Programming Language :: Python :: 3
Classifier: Programming Language :: Python :: 3.8
Classifier: Programming Language :: Python :: 3.9
Classifier: Programming Language :: Python :: 3.10
Classifier: Programming Language :: Python :: 3.11
Classifier: Programming Language :: Python :: 3.12
Classifier: Operating System :: OS Independent
Classifier: Topic :: Software Development :: Libraries :: Python Modules
Classifier: Topic :: System :: Systems Administration
Requires-Python: >=3.8
Requires-Dist: click>=8.1.7
Requires-Dist: rich>=13.7.0
Requires-Dist: requests>=2.31.0
Requires-Dist: pyyaml>=6.0.1
Requires-Dist: docker>=6.1.0
Requires-Dist: keyring>=24.3.0
Requires-Dist: cryptography>=41.0.7
Requires-Dist: pygments>=2.17.2
Dynamic: author
Dynamic: author-email
Dynamic: classifier
Dynamic: description
Dynamic: description-content-type
Dynamic: home-page
Dynamic: keywords
Dynamic: project-url
Dynamic: requires-dist
Dynamic: requires-python
Dynamic: summary
